nv_ingest/__init__.py
nv_ingest/version.py
nv_ingest/api/__init__.py
nv_ingest/api/main.py
nv_ingest/api/v1/__init__.py
nv_ingest/api/v1/health.py
nv_ingest/api/v1/ingest.py
nv_ingest/api/v1/metrics.py
nv_ingest/framework/__init__.py
nv_ingest/framework/orchestration/__init__.py
nv_ingest/framework/orchestration/ray/__init__.py
nv_ingest/framework/orchestration/ray/edges/__init__.py
nv_ingest/framework/orchestration/ray/edges/async_queue_edge.py
nv_ingest/framework/orchestration/ray/edges/ray_queue_edge.py
nv_ingest/framework/orchestration/ray/edges/threaded_queue_edge.py
nv_ingest/framework/orchestration/ray/examples/__init__.py
nv_ingest/framework/orchestration/ray/examples/pipeline_test_harness.py
nv_ingest/framework/orchestration/ray/examples/task_source_harness.py
nv_ingest/framework/orchestration/ray/examples/task_source_sink_harness.py
nv_ingest/framework/orchestration/ray/primitives/__init__.py
nv_ingest/framework/orchestration/ray/primitives/dataclasses.py
nv_ingest/framework/orchestration/ray/primitives/pipeline_monitor.py
nv_ingest/framework/orchestration/ray/primitives/pipeline_topology.py
nv_ingest/framework/orchestration/ray/primitives/ray_pipeline.py
nv_ingest/framework/orchestration/ray/primitives/ray_stat_collector.py
nv_ingest/framework/orchestration/ray/stages/__init__.py
nv_ingest/framework/orchestration/ray/stages/extractors/__init__.py
nv_ingest/framework/orchestration/ray/stages/extractors/audio_extractor.py
nv_ingest/framework/orchestration/ray/stages/extractors/chart_extractor.py
nv_ingest/framework/orchestration/ray/stages/extractors/docx_extractor.py
nv_ingest/framework/orchestration/ray/stages/extractors/html_extractor.py
nv_ingest/framework/orchestration/ray/stages/extractors/image_extractor.py
nv_ingest/framework/orchestration/ray/stages/extractors/infographic_extractor.py
nv_ingest/framework/orchestration/ray/stages/extractors/pdf_extractor.py
nv_ingest/framework/orchestration/ray/stages/extractors/pptx_extractor.py
nv_ingest-25.9.0.dist-info/licenses/LICENSE
nv_ingest-25.9.0.dist-info/METADATA
nv_ingest-25.9.0.dist-info/WHEEL
nv_ingest-25.9.0.dist-info/top_level.txt
nv_ingest-25.9.0.dist-info/RECORD
