Metadata-Version: 2.4
Name: nv-ingest
Version: 25.9.0
Summary: Python module for multimodal document ingestion
Author-email: Jeremy Dyer <jdyer@nvidia.com>
License:                                  Apache License
Project-URL: homepage, https://github.com/NVIDIA/nv-ingest
Project-URL: repository, https://github.com/NVIDIA/nv-ingest
Project-URL: documentation, https://docs.nvidia.com/nv-ingest
Classifier: Programming Language :: Python :: 3
Classifier: License :: OSI Approved :: MIT License
Classifier: Operating System :: OS Independent
License-File: LICENSE
Requires-Dist: azure-core>=1.32.0
Requires-Dist: click>=8.1.7
Requires-Dist: diskcache>=5.6.3
Requires-Dist: fastapi>=0.115.6
Requires-Dist: fastparquet>=2024.11.0
Requires-Dist: fsspec>=2024.10.0
Requires-Dist: gunicorn
Requires-Dist: h11>=0.16.0
Requires-Dist: httpx>=0.28.1
Requires-Dist: isodate>=0.7.2
Requires-Dist: langdetect>=1.0.9
Requires-Dist: minio>=7.2.12
Requires-Dist: openai>=1.82.0
Requires-Dist: opentelemetry-api>=1.27.0
Requires-Dist: opentelemetry-exporter-otlp>=1.27.0
Requires-Dist: opentelemetry-sdk>=1.27.0
Requires-Dist: nv-ingest-api==25.9.0
Requires-Dist: pydantic>2.0.0
Requires-Dist: pydantic-settings>2.0.0
Requires-Dist: pypdfium2==4.30.0
Requires-Dist: pytest>=8.0.2
Requires-Dist: pytest-mock>=3.14.0
Requires-Dist: pytest-cov>=6.0.0
Requires-Dist: build>=1.2.2
Requires-Dist: python-docx>=1.1.2
Requires-Dist: python-dotenv>=1.0.1
Requires-Dist: python-pptx>=1.0.2
Requires-Dist: prometheus-client
Requires-Dist: ray[all]>=2.49.0
Requires-Dist: redis>=5.2.1
Requires-Dist: requests>=2.28.2
Requires-Dist: scikit-learn>=1.6.0
Requires-Dist: scipy>=1.15.1
Requires-Dist: setuptools>=78.1.1
Requires-Dist: tabulate>=0.9.0
Requires-Dist: transformers>=4.47.0
Requires-Dist: tqdm>=4.67.1
Requires-Dist: uvicorn
Requires-Dist: pip
Requires-Dist: llama-index-embeddings-nvidia
Requires-Dist: opencv-python
Requires-Dist: pymilvus>=2.5.10
Requires-Dist: pymilvus[bulk_writer,model]
Requires-Dist: tritonclient
Requires-Dist: nvidia-riva-client==2.20.0
Requires-Dist: unstructured-client
Requires-Dist: markitdown
Dynamic: license-file
